{
    "package": "DNSmitmChecker",
    "info": {
        "title": "DNS.mitm Checker",
        "author": "Taylor Rodr\u00edguez",
        "category": "tool",
        "version": "0.4.0",
        "url": "https://git.tayri.dev/dns-mitm-checker/",
        "license": "BSD v3",
        "description": "Test Atmosph\u00e8re's DNS.mitm configuration",
        "details": "A Homebrew application that checks if Atmosph\u00e8re's DNS.mitm configuration is working correctly.\\n\\n- Minimal and fast.\\n- Checks if telemetry, connection tests, and firmware updates are blocked. \\n- Recognizes custom DNS redirection.\\n\\nI initially developed this software because Switch 90DNS Tester hadn't been updated in a long time. Now it's kind of its own thing. I think the primary use-case for this software is to ensure firmware updates are blocked, as future Atmosph\u00e8re updates aren't as guaranteed without SciresM."
    },
    "assets": [
        {
            "type": "icon",
            "url": "icon.png"
        },
        {
            "type": "banner",
            "url": "screen.png"
        },
        {
            "url": "https://git.tayri.dev/dns-mitm-checker.zip",
            "type": "zip",
            "zip": [
                {
                    "path": "/**/*",
                    "dest": "/",
                    "type": "update"
                }
            ]
        }
    ],
    "changelog": "v0.4.0\n\n- Revamped the user interface to be easier to read.\n- Added additional runtime and compile-time verification.\n- Reduced setsys service lifetime.\n- Optimized application size.\n\nv0.3.2\\n\\n- Added several minor performance improvements.\\n- Improved stability with additional compile-time checks.\\n- Fixed instance of undefined behaviour (introduced in v0.1.0).\\n\\nv0.3.1\\n\\n- Added support for detecting BrowseDNS and Nintendo Homebrew IP addresses.\\n- Optimized resolution of unblocked domain names.\\n- Improved stability with additional compile-time checks.\\n- Improved console responsiveness (regressed in v0.3.0).\\n\\nv0.3.0\\n\\n- Added check to ensure DNS.mitm is actually enabled.\\n- Removed superfluous domain name checks.\\n  - This focuses on domains actually used on the Nintendo Switch and avoids validating speculative blocking practices (security theatre).\\n- Fixed error display bug (introduced in v0.2.0)."
}
